MANIFEST.in
setup.py
baoquan/__init__.py
baoquan/main/__init__.py
baoquan/main/baoquan_client.py
baoquan/main/exception/__init__.py
baoquan/main/exception/invalid_argument_exception.py
baoquan/main/exception/server_exception.py
baoquan/main/util/__init__.py
baoquan/main/util/utils.py
baoquan/test/__init__.py
baoquan/test/baoquan_client_test.py
eagle_sdk.egg-info/PKG-INFO
eagle_sdk.egg-info/SOURCES.txt
eagle_sdk.egg-info/dependency_links.txt
eagle_sdk.egg-info/requires.txt
eagle_sdk.egg-info/top_level.txt