Metadata-Version: 1.0
Name: eagle-sdk
Version: 1.0.3
Summary: sdk for members to use the service of baoquan.com
Home-page: https://github.com/baoquan-hq/python-sdk.git
Author: sbwdlihao
Author-email: sbwdlihao@gmail.com
License: gpl-3.0
Keywords: baoquan eagle sdk
Platform: UNKNOWN
